token_interface/__init__.py
token_interface/core_styles.py
token_interface/material_theme_interface.py
token_interface/token_studio_interface.py
tokenizer_figma-1.0.6.dist-info/LICENSE
tokenizer_figma-1.0.6.dist-info/METADATA
tokenizer_figma-1.0.6.dist-info/WHEEL
tokenizer_figma-1.0.6.dist-info/top_level.txt
tokenizer_figma-1.0.6.dist-info/RECORD
