Metadata-Version: 2.1
Name: tokenizer-figma
Version: 1.0.6
Summary: A Python package for generating and managing design tokens for Figma, with Material Theme Builder integration and Tokens Studio plugin support.
Home-page: https://github.com/ByronFW/style-tokenizer-figma
Author: Byron
Author-email: byronforrestwhite@outlook.com
Classifier: Programming Language :: Python :: 3
Classifier: License :: OSI Approved :: MIT License
Classifier: Operating System :: OS Independent
Requires-Python: >=3.10
License-File: LICENSE
